helloworld.py
swachand_helloworld-0.0.3.dist-info/METADATA
swachand_helloworld-0.0.3.dist-info/WHEEL
swachand_helloworld-0.0.3.dist-info/top_level.txt
swachand_helloworld-0.0.3.dist-info/RECORD
