Metadata-Version: 2.1
Name: swachand-helloworld
Version: 0.0.3
Summary: Say Hello!
Home-page: https://github.com/SwatiChandak/swatichandak-helloworld
Author: Swati Chandak
Author-email: swati.chandak@publicissapient.com
License: UNKNOWN
Platform: UNKNOWN
Classifier: License :: OSI Approved :: MIT License
Classifier: Operating System :: OS Independent
Classifier: Programming Language :: Python :: 3
Classifier: Programming Language :: Python :: 3.6
Classifier: Programming Language :: Python :: 3.7
Requires-Dist: blessings (~=1.7)
Provides-Extra: dev
Requires-Dist: pytest (>=3.7) ; extra == 'dev'
